Audio_files_organizer_for_iphone/Audio_organizer.py
Audio_files_organizer_for_iphone/__init__.py
audio_files_organizer_iphone-1.0.0.dist-info/LICENSE
audio_files_organizer_iphone-1.0.0.dist-info/METADATA
audio_files_organizer_iphone-1.0.0.dist-info/WHEEL
audio_files_organizer_iphone-1.0.0.dist-info/entry_points.txt
audio_files_organizer_iphone-1.0.0.dist-info/top_level.txt
audio_files_organizer_iphone-1.0.0.dist-info/RECORD
