Metadata-Version: 2.1
Name: audio_files_organizer_iphone
Version: 1.0.0
Summary: A tool for organizing audio files for iPhone compatibility
Home-page: https://github.com/David-Sandeep/audio-files-organizer-iphone
Author: David Sandeep
Author-email: David Sandeep <davidsandeep1996@gmail.com>
License: MIT License
Keywords: audio,organizer,metadata,iphone
Classifier: Programming Language :: Python :: 3
Classifier: License :: OSI Approved :: MIT License
Classifier: Operating System :: OS Independent
Classifier: Intended Audience :: End Users/Desktop
Classifier: Topic :: Multimedia :: Sound/Audio :: Conversion
Requires-Python: >=3.7
License-File: LICENSE
Provides-Extra: gui
Requires-Dist: tkinter; extra == "gui"
